hello/__init__.py
hello/hello.py
hello_func-0.0.4.dist-info/METADATA
hello_func-0.0.4.dist-info/WHEEL
hello_func-0.0.4.dist-info/top_level.txt
hello_func-0.0.4.dist-info/RECORD
